polars_pc/__init__.py
polars_pc-0.0.2.dist-info/LICENSE
polars_pc-0.0.2.dist-info/METADATA
polars_pc-0.0.2.dist-info/WHEEL
polars_pc-0.0.2.dist-info/top_level.txt
polars_pc-0.0.2.dist-info/RECORD
