Metadata-Version: 2.1
Name: polars_pc
Version: 0.0.2
Summary: registers pyarrow-compute function as expressions to pc namespace
Author-email: Dean MacGregor <powertrading121@gmail.com>
Requires-Python: >=3.7
License-File: LICENSE
